README.md
setup.py
pyalpha/__init__.py
pyalpha/alpha.py
pyalpha/main.py
pyalpha/petri_net.py
pyalpha/reader.py
pyalpha.egg-info/PKG-INFO
pyalpha.egg-info/SOURCES.txt
pyalpha.egg-info/dependency_links.txt
pyalpha.egg-info/entry_points.txt
pyalpha.egg-info/not-zip-safe
pyalpha.egg-info/top_level.txt