Metadata-Version: 1.0
Name: pyalpha
Version: 0.1.0
Summary: A process mining tool written in Python3
Home-page: https://github.com/zhoudaxia233/pyalpha
Author: Zheng Zhou
Author-email: yootaoo@gmail.com
License: MIT
Keywords: alpha miner
Platform: UNKNOWN
